sphinxcontrib_kissapi-1.0.3-py3.5-nspkg.pth
sphinxcontrib/kissapi/__init__.py
sphinxcontrib/kissapi/def_render.py
sphinxcontrib/kissapi/introspect.py
sphinxcontrib/kissapi/manager.py
sphinxcontrib/kissapi/def_templates/macros.rst
sphinxcontrib/kissapi/def_templates/object.rst
sphinxcontrib_kissapi.egg-info/PKG-INFO
sphinxcontrib_kissapi.egg-info/SOURCES.txt
sphinxcontrib_kissapi.egg-info/dependency_links.txt
sphinxcontrib_kissapi.egg-info/namespace_packages.txt
sphinxcontrib_kissapi.egg-info/not-zip-safe
sphinxcontrib_kissapi.egg-info/requires.txt
sphinxcontrib_kissapi.egg-info/top_level.txt
sphinxcontrib_kissapi-1.0.3.dist-info/LICENSE
sphinxcontrib_kissapi-1.0.3.dist-info/METADATA
sphinxcontrib_kissapi-1.0.3.dist-info/WHEEL
sphinxcontrib_kissapi-1.0.3.dist-info/namespace_packages.txt
sphinxcontrib_kissapi-1.0.3.dist-info/top_level.txt
sphinxcontrib_kissapi-1.0.3.dist-info/RECORD
