Metadata-Version: 2.1
Name: sphinxcontrib-kissapi
Version: 1.0.3
Summary: Simple and flexible python API documentation generation plugin for Sphinx
Home-page: https://github.com/Azmisov/sphinxcontrib-kissapi
Author: Isaac Nygaard
Author-email: ozixtheorange@gmail.com
License: MIT
Keywords: sphinx automatic api generation documentation
Platform: any
Classifier: Development Status :: 5 - Production/Stable
Classifier: Intended Audience :: Developers
Classifier: License :: OSI Approved :: MIT License
Classifier: Operating System :: OS Independent
Classifier: Programming Language :: Python
Classifier: Programming Language :: Python :: 3
Classifier: Topic :: Documentation
Classifier: Topic :: Utilities
Classifier: Framework :: Sphinx
Classifier: Framework :: Sphinx :: Extension
Requires-Dist: Sphinx
Requires-Dist: docutils
Requires-Dist: jinja2
